memoq/__init__.py
memoq/server.py
memoq/util.py
memoq/webservice.py
pymemoq-0.2.dev6.dist-info/LICENSE
pymemoq-0.2.dev6.dist-info/METADATA
pymemoq-0.2.dev6.dist-info/WHEEL
pymemoq-0.2.dev6.dist-info/top_level.txt
pymemoq-0.2.dev6.dist-info/RECORD
