Metadata-Version: 2.1
Name: pymemoq
Version: 0.2.dev6
Summary: Python module to facilitate accessing the memoQ API.
Home-page: https://github.com/leonidessaguisagjr/pymemoq
Author: Leonides T. Saguisag Jr.
Author-email: leonidessaguisagjr@gmail.com
License: MIT
Platform: UNKNOWN
Classifier: Development Status :: 3 - Alpha
Classifier: Intended Audience :: Developers
Classifier: License :: OSI Approved :: MIT License
Classifier: Programming Language :: Python
Classifier: Programming Language :: Python :: 3
Classifier: Programming Language :: Python :: 3.6
Classifier: Programming Language :: Python :: 3.7
Classifier: Programming Language :: Python :: 3.8
Classifier: Topic :: Software Development :: Libraries
Classifier: Topic :: Software Development :: Localization
Requires-Dist: zeep
